mixin.py
setup.py
mixin.egg-info/PKG-INFO
mixin.egg-info/SOURCES.txt
mixin.egg-info/dependency_links.txt
mixin.egg-info/top_level.txt