Metadata-Version: 1.1
Name: mixin
Version: 1.1
Summary: python mixin tool
Home-page: https://github.com/yupeng820921/pymixin
Author: yupeng
Author-email: yupeng0921@gmail.com
License: MIT
Keywords: mixin
Platform: any
Classifier: Programming Language :: Python :: 2.6
Classifier: Programming Language :: Python :: 2.7
Classifier: Programming Language :: Python :: 3
